metaphlan/__init__.py
metaphlan/metaphlan.py
metaphlan/strainphlan.py
metaphlan/metaphlan_databases/README.txt
metaphlan/utils/VallesColomerM_2022_Jan21_thresholds.tsv
metaphlan/utils/VallesColomerM_2022_Nov19_thresholds.tsv
metaphlan/utils/__init__.py
metaphlan/utils/add_metadata_tree.py
metaphlan/utils/calculate_diversity.R
metaphlan/utils/consensus_markers.py
metaphlan/utils/create_toy_database.py
metaphlan/utils/database_controller.py
metaphlan/utils/external_exec.py
metaphlan/utils/extract_markers.py
metaphlan/utils/fix_relab_mpa4.py
metaphlan/utils/merge_metaphlan_tables.py
metaphlan/utils/merge_vsc_tables.py
metaphlan/utils/metaphlan2krona.py
metaphlan/utils/mpa_vJan21_CHOCOPhlAnSGB_202103_SGB2GTDB.tsv
metaphlan/utils/mpa_vJan21_CHOCOPhlAnSGB_202103_size.txt.bz2
metaphlan/utils/mpa_vJan25_CHOCOPhlAnSGB_202503_SGB2GTDB.tsv
metaphlan/utils/mpa_vJan25_CHOCOPhlAnSGB_202503_size.txt.bz2
metaphlan/utils/mpa_vJun23_CHOCOPhlAnSGB_202307_SGB2GTDB.tsv
metaphlan/utils/mpa_vJun23_CHOCOPhlAnSGB_202307_size.txt.bz2
metaphlan/utils/mpa_vJun23_CHOCOPhlAnSGB_202403_SGB2GTDB.tsv
metaphlan/utils/mpa_vJun23_CHOCOPhlAnSGB_202403_size.txt.bz2
metaphlan/utils/mpa_vOct22_CHOCOPhlAnSGB_202212_SGB2GTDB.tsv
metaphlan/utils/mpa_vOct22_CHOCOPhlAnSGB_202212_size.txt.bz2
metaphlan/utils/oct22_fix_tax.tsv
metaphlan/utils/parallelisation.py
metaphlan/utils/phylophlan_controller.py
metaphlan/utils/plot_bug.py
metaphlan/utils/plot_tree_graphlan.py
metaphlan/utils/pyphlan.py
metaphlan/utils/read_fastx.py
metaphlan/utils/sample2markers.py
metaphlan/utils/sgb_to_gtdb_profile.py
metaphlan/utils/strain_transmission.py
metaphlan/utils/util_fun.py
metaphlan/utils/treeshrink/run_treeshrink.py
metaphlan/utils/treeshrink/treeshrink.py
metaphlan/utils/treeshrink/R_scripts/Rfunctions.R
metaphlan/utils/treeshrink/R_scripts/find_d.R
metaphlan/utils/treeshrink/R_scripts/find_outliers.R
metaphlan/utils/treeshrink/R_scripts/find_outliers_IQR.R
metaphlan/utils/treeshrink/R_scripts/find_outliers_IQR.log.R
MetaPhlAn-4.2.4.dist-info/METADATA
MetaPhlAn-4.2.4.dist-info/WHEEL
MetaPhlAn-4.2.4.dist-info/entry_points.txt
MetaPhlAn-4.2.4.dist-info/top_level.txt
MetaPhlAn-4.2.4.dist-info/RECORD
