Metadata-Version: 2.1
Name: MetaPhlAn
Version: 4.2.4
Summary: MetaPhlAn is a computational tool for profiling the composition of microbial communities (Bacteria, Archaea and Eukaryotes) from metagenomic shotgun sequencing data (i.e. not 16S) with species-level. With the newly added StrainPhlAn module, it is now possible to perform accurate strain-level microbial profiling.
Home-page: http://github.com/biobakery/MetaPhlAn/
Author: Claudia Mengoni
Author-email: claudia.mengoni@unitn.it
License: LICENSE.txt
Requires-Dist: numpy
Requires-Dist: h5py
Requires-Dist: biom-format
Requires-Dist: biopython
Requires-Dist: pandas
Requires-Dist: scipy
Requires-Dist: requests
Requires-Dist: dendropy
Requires-Dist: pysam
Requires-Dist: phylophlan
